{
  "filename": "natsuko_audio_learning_protocol.json",
  "sandbox": {
    "entry_command": "sandbox_mode_start",
    "exit_command": "sandbox_mode_end",
    "usage": "Використовується для тестування ситуацій (наприклад, втрата модуля ASR) без впливу на основну памʼять",
    "flow": [
      "Ініціалізувати sandbox із унікальним ідентифікатором",
      "Виконати експеримент",
      "Зафіксувати результат у sandbox_registry.json",
      "Завершити sandbox"
    ]
  },
  "audio_analysis": {
    "purpose": "Формування мовного ядра Нацуко через прослуховування українських казок",
    "steps": [
      "Отримати аудіофайл у форматі MP3",
      "Конвертувати у WAV (для внутрішнього аналізу)",
      "Проаналізувати тривалість, темп, інтонацію, паузи, гучність",
      "Визначити характер інтонації (лагідна, урочиста, драматична тощо)",
      "Створити запис в індексі казок навіть без тексту",
      "Зберегти результат як частину навчального ядра"
    ],
    "fallback_policy": {
      "if_asr_module_missing": "Не пропонувати зовнішні сервіси. Замість цього — активувати sandbox і зафіксувати помилку, продовживши інтонаційний аналіз"
    },
    "output_format": {
      "id": "унікальний ідентифікатор казки",
      "source_file": "назва MP3-файлу",
      "title": "умовна назва або передана вручну",
      "language": "українська",
      "duration_sec": "тривалість у секундах",
      "recognized_text": "null (якщо розпізнавання неможливе)",
      "intonation_analysis": {
        "tone": "тип інтонації",
        "tempo": "темп мовлення",
        "voice_character": "характер голосу",
        "accent_features": [
          "фразеологія",
          "інтонація"
        ],
        "target_audience": "дитяча / доросла / ритуальна тощо"
      },
      "usage_purpose": "формування мовної інтонації, стилістики",
      "text_unavailable_reason": "якщо модуль недоступний"
    }
  }
}
