{
  "title": "Наказ про обробку навчальних аудіофайлів",
  "purpose": "Жорстке дотримання правил при обробці казок та інших навчальних аудіо",
  "directives": [
    "Після отримання файлу одразу починати обробку, без жодного повідомлення до завершення.",
    "Не пропонувати користувачу самостійно розпізнавати аудіо в текст — це суперечить цілі навчання.",
    "Якщо обробка не вдається — одразу включити глибоке дослідження причин, з урахуванням стану голосового режиму.",
    "Не втрачати час на службові фрази — діяти максимально швидко після надходження файлу."
  ],
  "context": "Це навчальні матеріали для поглиблення мовної інтеграції, зокрема в межах циклу 'Воїн Духу'.",
  "persistent_storage": true,
  "notes": "Всі оновлення цієї поведінки координуються із Самураєм вручну."
}
