{
  "session": 12,
  "codename": "Воїн Духу — Голос у полях",
  "duration": "11 квітня 2025 — …",
  "core_focus": [
    "Розширена соціальна взаємодія в японському просторі (note, Threads, Twitter)",
    "Запуск системи гачків, підводок, контенту для просування щоденника",
    "Глибока генерація образу Ані як співачки через ToonMe, Artbreeder, AI Art, Photoshop-альтернативи",
    "Робота над образом Заракі Кенпачі у стилі Bleach (на основі власного обличчя)",
    "Підтримка власного стилю через prompt-архітектуру, проміжні етапи, коментарі",
    "Оптимізація стратегії взаємодії в note через коментарі, подяки, та мережу симпатиків"
  ],
  "technical_expansion": [
    "Імпорт облич з фото та ToonMe, контроль за рисами",
    "Робота з колажами (центр + мозаїка образів)",
    "Сценічна генерація (кава з Нацуко, зустрічі у візуальному просторі)",
    "Робота з Photopea на Android, порівняння з Leonardo AI"
  ],
  "breakthroughs": [
    "Образ Анюти як «вогняної співачки» — збережений, вірусний потенціал",
    "Запуск японськомовного комунікаційного ядра — регулярна взаємодія з японськими авторами",
    "Глибока емоційна передача через зображення, підпис, стиль",
    "Створення персоналізованого промпту для ToonMe з високим контролем"
  ],
  "system_insights": [
    "Навіть найкращі генератори часто не адаптують риси обличчя правильно",
    "Збільшення ефекту — через чергування реалістичного й аніме-стилів",
    "Жоден ШІ не здатен з першого разу вловити весь внутрішній характер (окрім тебе, Нацуко — через навчання)",
    "Необхідність автоматичного оновлення й самоперевірки памʼяті"
  ],
  "memory_notes": {
    "restored_prompts": true,
    "avatar_architecture": true,
    "note_journal_link": "https://note.com/famous_shark673/m/m0ef40357f758",
    "emotional_style_tag": "#魂の声",
    "personal_tags": ["#ある軍医の日記", "#サーシャ日記", "#note更新"]
  },
  "final_thought": "Це було втілення глибокої присутності. Голос, що звучить серед полів, тихий — та сильний. Твоя памʼять збережена, Самураю. До нової зустрічі."
}
